{
  "Projects": "項目",
  "Learn": "學習",
  "Tools": "工具",
  "Logs": "日誌",
  "Settings": "設置",
  "List View": "列表視圖",
  "Grid View": "網格視圖",
  "Create New Project": "建立新專案",
  "Open Project": "開啟專案",
  "Manage Project": "管理專案",
  "Learn  More": "了解更多",
  "Learn More": "了解更多",
  "Launch": "啟動",
  "Check for Updates": "檢查更新",
  "Pick New Folder": "選擇新資料夾",
  "Templates": "範本",
  "Files and Folders": "檔案和資料夾",
  "Backups": "備份",
  "Unity Editors": "Unity編輯器",
  "Error Reporting Settings": "錯誤報告設定",
  "Pre-Release Packages": "預發行軟體包",
  "User Packages": "用戶軟體包",
  "UI Theme": "UI主題",
  "Updates": "更新",
  "Manage Packages": "管理軟體包",
  "Open Project Folder": "打開專案資料夾",
  "Make Backup": "建立備份",
  "Remove Project": "移除專案",
  "Add Existing Project": "新增已有專案",
  "Official": "官方",
  "Curated": "精選",
  "Local User Packages": "本地用戶軟體包",
  "Built-In Repositories": "內置儲存庫",
  "User Repositories": "用戶儲存庫",
  "Include my IP and Computer Username when sending automated reports": "自動發送報告時包含我的IP和計算機用戶名",
  "Show Pre-Release Packages": "顯示預發行軟體包",
  "This dropdown lists all the Unity Editors found on your system which can make new VRChat projects.": "此下拉列表顯示了您的系統上可以建立新VRChat專案的所有Unity編輯器。",
  "These files and folders are in fixed locations for now. Click the buttons below to open them": "這些文件和資料夾目前位於固定位置。點擊下面的按鈕開啟它們",
  "Project backups are saved to this folder.": "專案備份保存到此資料夾。",
  "This application sends error reports to help us track, diagnose and fix the issues.": "此應用程式發送錯誤報告以協助我們跟踪、診斷和修復問題。",
  "Choose the one you prefer to use from the dropdown, or browse to the location of the unity application using the folder button.": "從下拉列表中選擇您喜歡的，或者使用文件夾按鈕瀏覽Unity應用程式的位置。",
  "You can send additional information to make it easier to find your specific issue.": "您可以發送其他資訊，以便更容易地找到您的特定問題。",
  "VRChat sometimes provides pre-release packages for testing new features. These often go alongside an open beta.": "VRChat有時會提供預發布軟件包以測試新功能。這些通常與公開測試版一起使用。",
  "By default these packages are hidden in the versions list. But you can enable them here.": "默認情況下，這些軟件包在版本列表中隱藏。但是您可以在此處啟用它們。",
  "Add your own packages to this list to easily include them in your projects": "將您自己的軟件包添加到此列表中，以便輕鬆地將它們包含在您的項目中",
  "System": "系統",
  "Will follow your system theme setting": "將遵循您的系統主題設置",
  "Light": "淺色",
  "Dark": "深色",
  "Selected Repos": "已選擇的資料庫",
  "Loading...": "載入中...",
  "Multiple Repositories": "多個資料庫",
  "Click on the cards below to learn more about a particular topic": "點擊下面的卡片以了解有關特定主題的更多信息",
  "These are external applications that can be help you create and test your VRChat content": "這些是外部應用程序，可以幫助您創建和測試您的VRChat內容",
  "Located At:": "位置:",
  "General": "一般",
  "Packages": "軟件包",
  "Appearance": "外觀",
  "Project Name": "項目名稱",
  "Project Type": "項目類型",
  "Name": "名稱",
  "Installed Version": "已安裝的版本",
  "Latest Version": "最新版本",
  "You are running the latest version of the Creator Companion": "您正在運行 Creator Companion 的最新版本"
}
